[{"Name":"무쇠갑옷","Effect":9,"Info":"무쇠로 만들어져 튼튼한 갑옷입니다.","IsBuy":true,"IsSell":false,"ItemType":"방어구","IsEquip":false,"Price":2200},{"Name":"스파르타의 창","Effect":7,"Info":"스파르타의 전사들이 사용했다는 전설의 창","IsBuy":true,"IsSell":false,"ItemType":"무기","IsEquip":false,"Price":3200},{"Name":"낡은 검","Effect":2,"Info":"쉽게 볼 수 있는 낡은 검 입니다.","IsBuy":false,"IsSell":false,"ItemType":"무기","IsEquip":false,"Price":600},{"Name":"수련자 갑옷","Effect":5,"Info":"수련에 도움을 주는 갑옷입니다.","IsBuy":false,"IsSell":false,"ItemType":"방어구","IsEquip":false,"Price":1000},{"Name":"스파르타의 갑옷","Effect":15,"Info":"스파르타의 전사들이 사용했다는 전설의 갑옷입니다.","IsBuy":false,"IsSell":false,"ItemType":"방어구","IsEquip":false,"Price":3500},{"Name":"청동 도끼","Effect":5,"Info":"어디선가 사용됐던거 같은 도끼입니다.","IsBuy":false,"IsSell":false,"ItemType":"무기","IsEquip":false,"Price":1500},{"Name":"나만의 아이템","Effect":100,"Info":"나만의 아이템입니다. 겁나 셉니다.","IsBuy":false,"IsSell":false,"ItemType":"무기","IsEquip":false,"Price":9999}]